AUTHOR.txt
CMakeLists.txt
Changelog.md
LICENSE
MANIFEST.in
Makefile-custom
Makefile.am
README.rst
setup.py
ais/__init__.py
ais/io.py
ais/lut.py
ais/nmea.py
ais/nmea_messages.py
ais/nmea_queue.py
ais/stats.py
ais/tag_block.py
ais/uscg.py
ais/util.py
ais/vdm.py
ais/compatibility/__init__.py
ais/compatibility/gpsd.py
ais/stream/__init__.py
ais/stream/checksum.py
bin/aisdecode
docs/README.org
docs/dac_fi.org
docs/mid.csv
docs/msg_creation_guide.org
libais.egg-info/PKG-INFO
libais.egg-info/SOURCES.txt
libais.egg-info/dependency_links.txt
libais.egg-info/entry_points.txt
libais.egg-info/requires.txt
libais.egg-info/top_level.txt
src/Makefile-custom
src/libais/Makefile-custom
src/libais/ais.cpp
src/libais/ais.h
src/libais/ais10.cpp
src/libais/ais12.cpp
src/libais/ais14.cpp
src/libais/ais15.cpp
src/libais/ais16.cpp
src/libais/ais17.cpp
src/libais/ais18.cpp
src/libais/ais19.cpp
src/libais/ais1_2_3.cpp
src/libais/ais20.cpp
src/libais/ais21.cpp
src/libais/ais22.cpp
src/libais/ais23.cpp
src/libais/ais24.cpp
src/libais/ais25.cpp
src/libais/ais26.cpp
src/libais/ais27.cpp
src/libais/ais4_11.cpp
src/libais/ais5.cpp
src/libais/ais6.cpp
src/libais/ais7_13.cpp
src/libais/ais8.cpp
src/libais/ais8_1_22.cpp
src/libais/ais8_1_26.cpp
src/libais/ais8_200.cpp
src/libais/ais8_366.cpp
src/libais/ais8_366_22.cpp
src/libais/ais8_367.cpp
src/libais/ais9.cpp
src/libais/ais_bitset.cpp
src/libais/ais_decode_normed.cpp
src/libais/ais_py.cpp
src/libais/decode_body.cpp
src/libais/decode_body.h
src/libais/vdm.cpp
src/libais/vdm.h
src/test/Makefile-custom
src/test/ais10_test.cc
src/test/ais12_test.cc
src/test/ais14_test.cc
src/test/ais15_test.cc
src/test/ais16_test.cc
src/test/ais17_test.cc
src/test/ais18_test.cc
src/test/ais19_test.cc
src/test/ais1_2_3_test.cc
src/test/ais20_test.cc
src/test/ais21_test.cc
src/test/ais22_test.cc
src/test/ais23_test.cc
src/test/ais24_test.cc
src/test/ais25_test.cc
src/test/ais26_test.cc
src/test/ais27_test.cc
src/test/ais4_11_test.cc
src/test/ais5_test.cc
src/test/ais6_test.cc
src/test/ais7_13_test.cc
src/test/ais8_1_22_test.cc
src/test/ais8_200_test.cc
src/test/ais8_366_test.cc
src/test/ais8_367_test.cc
src/test/ais8_test.cc
src/test/ais9_test.cc
