Metadata-Version: 1.1
Name: libais
Version: 0.17
Summary: Automatic Identification System decoding - ship tracking
Home-page: https://github.com/schwehr/libais
Author: Kurt Schwehr
Author-email: schwehr@gmail.com
License: Apache 2.0
Platform: POSIX
Classifier: License :: OSI Approved :: Apache Software License
Classifier: Development Status :: 4 - Beta
Classifier: Intended Audience :: Science/Research
Classifier: Operating System :: Android
Classifier: Operating System :: iOS
Classifier: Operating System :: POSIX
Classifier: Programming Language :: C++
Classifier: Programming Language :: Python :: 2.7
Classifier: Programming Language :: Python :: 3.4
Classifier: Programming Language :: Python :: Implementation :: CPython
Classifier: Topic :: Communications
Classifier: Topic :: Scientific/Engineering :: Information Analysis
Classifier: Topic :: System :: Networking
Classifier: Topic :: Scientific/Engineering :: GIS
Classifier: Topic :: Scientific/Engineering :: Interface Engine/Protocol Translator
